lungo_cli/__init__.py
lungo_cli/app/__init__.py
lungo_cli/app/main.py
lungo_cli/app/state.py
lungo_cli/commands/__init__.py
lungo_cli/commands/base.py
lungo_cli/commands/check.py
lungo_cli/commands/down.py
lungo_cli/commands/install.py
lungo_cli/commands/list.py
lungo_cli/commands/uninstall.py
lungo_cli/commands/up.py
lungo_cli/core/__init__.py
lungo_cli/core/app.py
lungo_cli/core/console.py
lungo_cli/core/constants.py
lungo_cli/core/container.py
lungo_cli/core/context.py
lungo_cli/core/database.py
lungo_cli/core/file.py
lungo_cli/core/network.py
lungo_cli/core/plugin.py
lungo_cli/core/renderer.py
lungo_cli/core/storage.py
lungo_cli/helpers/__init__.py
lungo_cli/helpers/common.py
lungo_cli/helpers/crypto.py
lungo_cli/helpers/format.py
lungo_cli/models/__init__.py
lungo_cli/models/base.py
lungo_cli/models/config.py
lungo_cli/models/context.py
lungo_cli/models/plugin.py
lungo_cli/models/users.py
lungo_cli/plugins/__init__.py
lungo_cli/plugins/filebrowser/Dockerfile.jinja
lungo_cli/plugins/filebrowser/README.md
lungo_cli/plugins/filebrowser/compose/compose.yaml.jinja
lungo_cli/plugins/filebrowser/config/config_export.yaml.jinja
lungo_cli/plugins/filebrowser/config/settings.yaml.jinja
lungo_cli/plugins/filebrowser/config/users_export.yaml.jinja
lungo_cli/plugins/filebrowser/nginx/site.conf.jinja
lungo_cli/plugins/filebrowser/oathkeeper/access_rules.yaml.jinja
lungo_cli/plugins/filebrowser/plugin.py
lungo_cli/plugins/filebrowser/web/lib/icons/FolderOutline.svelte
lungo_cli/plugins/filebrowser/web/lib/icons/FolderSolid.svelte
lungo_cli/plugins/filebrowser/web/lib/icons/index.ts
lungo_cli/plugins/filebrowser/web/routes/[...url]/+page.svelte
lungo_cli/plugins/jupyterhub/Dockerfile.jinja
lungo_cli/plugins/jupyterhub/README.md
lungo_cli/plugins/jupyterhub/compose/compose.yaml.jinja
lungo_cli/plugins/jupyterhub/config/config.py.jinja
lungo_cli/plugins/jupyterhub/config/sudoers
lungo_cli/plugins/jupyterhub/nginx/site.conf.jinja
lungo_cli/plugins/jupyterhub/plugin.py
lungo_cli-0.5.12.dist-info/LICENSE
lungo_cli-0.5.12.dist-info/METADATA
lungo_cli-0.5.12.dist-info/WHEEL
lungo_cli-0.5.12.dist-info/entry_points.txt
lungo_cli-0.5.12.dist-info/RECORD
