Metadata-Version: 2.1
Name: lungo-cli
Version: 0.5.12
Summary: A user-friendly home lab setup designed for small-to-mid-scale on-premises hosting.
Home-page: https://github.com/raymond-u/lungo
Keywords: homelab,self-host
Author: raymond-u
Author-email: 36328498+raymond-u@users.noreply.github.com
Requires-Python: >=3.12,<4.0
Classifier: Programming Language :: Python :: 3
Classifier: Programming Language :: Python :: 3.12
Classifier: Programming Language :: Python :: 3.13
Requires-Dist: aenum (>=3.1.15,<4.0.0)
Requires-Dist: cryptography (>=43.0.3,<44.0.0)
Requires-Dist: jinja2 (>=3.1.4,<4.0.0)
Requires-Dist: packaging (>=24.2,<25.0)
Requires-Dist: platformdirs (>=4.3.6,<5.0.0)
Requires-Dist: pydantic-yaml (>=1.3.0,<2.0.0)
Requires-Dist: pydantic[email] (>=2.9.2,<3.0.0)
Requires-Dist: requests (>=2.32.3,<3.0.0)
Requires-Dist: typer (>=0.13.0,<0.14.0)
Project-URL: Documentation, https://raymond-u.github.io/lungo/
Project-URL: Repository, https://github.com/raymond-u/lungo
